pyimessage3/__init__.py
pyimessage3/imessage.py
pyimessage3-0.0.1.dist-info/METADATA
pyimessage3-0.0.1.dist-info/WHEEL
pyimessage3-0.0.1.dist-info/top_level.txt
pyimessage3-0.0.1.dist-info/RECORD
