Metadata-Version: 2.1
Name: pyimessage3
Version: 0.0.1
Summary: for macos to read and send message
Author: liuyonghong
Author-email: 59225176@qq.com
